DemoProfile/__init__.py
demoProfile-0.0.4.dist-info/LICENCE
demoProfile-0.0.4.dist-info/METADATA
demoProfile-0.0.4.dist-info/WHEEL
demoProfile-0.0.4.dist-info/top_level.txt
demoProfile-0.0.4.dist-info/RECORD
