Metadata-Version: 2.1
Name: demoProfile
Version: 0.0.4
Summary: a package that generates profile picture from your name
Author: Sheikh Umaid
Author-email: sheikhumaid@pm.me
Keywords: demo,profile_picture,alphabet profile,django,sheikh umaid
Classifier: Development Status :: 1 - Planning
Classifier: Intended Audience :: Developers
Classifier: Programming Language :: Python :: 3
Classifier: Operating System :: Unix
Classifier: Operating System :: MacOS :: MacOS X
Classifier: Operating System :: Microsoft :: Windows
License-File: LICENCE
Requires-Dist: pillow
